{"frames":{"loadingReal6":{"frame":{"x":0,"y":0,"w":1600,"h":900},"rotated":false,"trimmed":false,"spriteSourceSize":{"x":0,"y":0,"w":1600,"h":900},"sourceSize":{"w":1600,"h":900}},"loadingReal7":{"frame":{"x":0,"y":901,"w":1600,"h":900},"rotated":false,"trimmed":false,"spriteSourceSize":{"x":0,"y":0,"w":1600,"h":900},"sourceSize":{"w":1600,"h":900}},"loadingReal0":{"frame":{"x":0,"y":1802,"w":1600,"h":900},"rotated":false,"trimmed":false,"spriteSourceSize":{"x":0,"y":0,"w":1600,"h":900},"sourceSize":{"w":1600,"h":900}},"loadingReal1":{"frame":{"x":1601,"y":0,"w":1600,"h":900},"rotated":false,"trimmed":false,"spriteSourceSize":{"x":0,"y":0,"w":1600,"h":900},"sourceSize":{"w":1600,"h":900}},"loadingReal2":{"frame":{"x":1601,"y":901,"w":1600,"h":900},"rotated":false,"trimmed":false,"spriteSourceSize":{"x":0,"y":0,"w":1600,"h":900},"sourceSize":{"w":1600,"h":900}},"loadingReal3":{"frame":{"x":1601,"y":1802,"w":1600,"h":900},"rotated":false,"trimmed":false,"spriteSourceSize":{"x":0,"y":0,"w":1600,"h":900},"sourceSize":{"w":1600,"h":900}},"loadingReal4":{"frame":{"x":0,"y":2703,"w":1600,"h":900},"rotated":false,"trimmed":false,"spriteSourceSize":{"x":0,"y":0,"w":1600,"h":900},"sourceSize":{"w":1600,"h":900}},"loadingReal5":{"frame":{"x":1601,"y":2703,"w":1600,"h":900},"rotated":false,"trimmed":false,"spriteSourceSize":{"x":0,"y":0,"w":1600,"h":900},"sourceSize":{"w":1600,"h":900}}},"meta":{"app":"https://www.leshylabs.com/apps/sstool/","version":"Leshy SpriteSheet Tool v0.8.4","image":"loading.png","size":{"w":3201,"h":3603},"scale":1}}